frr/__init__.py
frr/__main__.py
frr/base.py
frr/core.py
frr/utils.py
fast_reflection_removal-1.1.dist-info/METADATA
fast_reflection_removal-1.1.dist-info/WHEEL
fast_reflection_removal-1.1.dist-info/entry_points.txt
fast_reflection_removal-1.1.dist-info/top_level.txt
fast_reflection_removal-1.1.dist-info/RECORD
